extraction/__init__.py
IndonesiaEarthquakeinfo-0.5.dist-info/LICENSE
IndonesiaEarthquakeinfo-0.5.dist-info/METADATA
IndonesiaEarthquakeinfo-0.5.dist-info/WHEEL
IndonesiaEarthquakeinfo-0.5.dist-info/top_level.txt
IndonesiaEarthquakeinfo-0.5.dist-info/RECORD
